globalmart_api/__init__.py
globalmart_api/process_json.py
AkshayCDTLib-0.1.dist-info/LICENSE.txt
AkshayCDTLib-0.1.dist-info/METADATA
AkshayCDTLib-0.1.dist-info/WHEEL
AkshayCDTLib-0.1.dist-info/top_level.txt
AkshayCDTLib-0.1.dist-info/RECORD
